Workbook

Sheet Données Exercice
C1: Valeur | D1: Amortissement | F1: tx interet
B2: Rachat droit de bail | C2: 30000
B3: Frais notaire | C3: 3300 | D3: 3 | E3: ans
B4: Travaux HT | C4: 6450 | D4: 10 | E4: ans
B5: Matérielc HT | C5: 3150 | E5: ans
B6: Stock | C6: / | D6: 30 | E6: jours
B7: Créances clients | C7: / | D7: 15 | E7: jours
B8: dettes fournisseurs | C8: / | D8: 30 | E8: jours
B9: Capital fixé | C9: 7500
B10: Comptes courants | C10: 10000
B11: Emprunt | C11: 45000 | D11: 5 | E11: ans | F11: 0.02
B12: Prêt d'honneur BULTZA | C12: 4000 | D12: 4 | E12: ans
B13: Salaire annuel 2019 | C13: 8790 | F13: 0.4
B14: Salaire annuel 2020 | C14: 9054 | E14: ans | F14: 0.4
B15: Rémunération 2019 | C15: 1000
B16: Rémunération 2020 | C16: 1200

Sheet Plan financement
C3: BESOIN | E3: RESSOURCES
C4: Investissement incorporels HT | D4: =D5+D6 -> 33300 | E4: Apports personnels ou capital | F4: =F5+F6 -> 17500
C5: ='Données Exercice'!B2 -> Rachat droit de bail | D5: ='Données Exercice'!C2 -> 30000 | E5: capital : | F5: ='Données Exercice'!C9 -> 7500
C6: Frais de constitution : | D6: ='Données Exercice'!C3 -> 3300 | E6: compte courant : | F6: ='Données Exercice'!C10 -> 10000
C7: Investissement Corporels HT | D7: =D8+D9+D10 -> 9600 | E7: Emprunts | F7: =F8 -> 45000
C8: Matériel : | D8: ='Données Exercice'!C5 -> 3150 | E8: Emprunts : | F8: ='Données Exercice'!C11 -> 45000
C9: Installation enseigne : | D9: 0 | E9: ='Données Exercice'!B12 -> Prêt d'honneur BULTZA | F9: ='Données Exercice'!C12 -> 4000
C10: Travaux : | D10: ='Données Exercice'!C4 -> 6450
C11: BFR
C12: Stock :
C13: Dettes :
C14: Créances :
C15: Réserve de trésorerie
C16: TOTAL BESOINS | E16: TOTAL RESSOURCES
C19: Calcul BFR :
C20: STOCK | D20: =165000*0.57*'Données Exercice'!D6/365 -> 7730.137
C21: + CREANCE
C22: - DETTES | D22: =165000*1.2*15/365 -> 8136.9863
C23: = BFR | D23: =D20+D21-D22 -> -406.84932

Sheet Tableaux ammortissement
B2: Tableau ammortissement du frais de constitution | H2: Tableau ammortissement du aquisition de matériel
B3: Années | C3: V.O.H.T | D3: Dotations | E3: Cumul dotation | F3: VNC | H3: Années | I3: V.O.H.T | J3: Dotations | K3: Cumul dotation | L3: VNC
B4: 2019 | C4: 3300 | D4: =$C$4/3 -> 1100 | E4: =D4 -> 1100 | F4: =C4-E4 -> 2200 | H4: 2019
B5: 2020 | C5: =F4 -> 2200 | D5: =$C$4/3 -> 1100 | E5: =E4+D5 -> 2200 | F5: =C4-E5 -> 1100 | H5: 2020
B6: 2021 | C6: =F5 -> 1100 | D6: =$C$4/3 -> 1100 | E6: =D6 -> 1100 | F6: =C6-E6 -> 0 | H6: 2021
H7: 2022
H8: 2023
B10: Tableau ammortissement du travaux pt de vente | H10: Tableau ammortissement du installation entreprise
B11: Années | C11: V.O.H.T | D11: Dotations | E11: Cumul dotation | F11: VNC | H11: Années | I11: V.O.H.T | J11: Dotations | K11: Cumul dotation | L11: VNC
B12: 2019 | H12: 2019
B13: 2020 | H13: 2020
B14: 2021 | H14: 2021
B15: 2022 | H15: 2022
B16: 2023 | H16: 2023
B17: 2024
B18: 2025
B19: 2026
B20: 2027
B21: 2028

Sheet Tableaux remboursement
B2: Mois | C2: Emprunts restant du | D2: Intérêt | E2: Amortissement | F2: Mensualité | G2: Valeurs nette
B3: 1
B4: 2 | I4: tx mensuel | J4: ='Données Exercice'!C16/12 -> 100
B5: 3
B6: 4
B7: 5
B8: 6
B9: 7
B10: 8
B11: 9
B12: 10
B13: 11
B14: 12
B15: 13
B16: 14
... B86: 84

Sheet Compte de résultat A.C.I
B2: CHARGE | E2: PRODUITS
C3: 2019 | D3: 2020 | F3: 2019 | G3: 2020
B4: Achats | E4: Chiffre d'affaires
B5: Achats | E5: Ventes de produits finis
B6: Achats de marchandises | E6: Ventes de marchandises
B7: Achats non stockés (eau,EDF, gaz, fournitures…) | E7: Ventes de prestationsde services
B8: Services e externes | E8: Subvention d'explotation
B9: Redevances crédit-bail
B10: Loyer
B11: Entretien/Réparation
B12: Assurances
B13: Honoraires
B14: Publicité
B15: Déplacements, missions
B16: Frais postaux/Téléphone
B17: Services bancaires
B18: Autres
B20: Impôts et taxes
B21: CET
... B29: Impot societes
B30: TOTAL DES CHARGES | E30: TOTAL DES PRODUITS
B31: RESULTAT
B32: TOTAL
B34: CALCUL CAF
B39: CALCUL Autofinancement
